Metadata-Version: 2.1
Name: tfmc-machine-parts-pp
Version: 0.2.1
Summary: Planted partitions over machine part data with part-of relations
Home-page: https://github.com/tfmcdigital/tfmc-data-in-brief-article/tree/main/python
Author: Daniel Bakkelund, Marcel Castro
Author-email: daniel.bakkelund@ifi.uio.no, marcel.cavalcantidecastro@technipfmc.com
License: UNKNOWN
Platform: UNKNOWN
Classifier: Programming Language :: Python :: 3
Classifier: License :: OSI Approved :: GNU Lesser General Public License v3 or later (LGPLv3+)
Classifier: Development Status :: 3 - Alpha
Classifier: Operating System :: OS Independent
Requires-Python: >=3.0
